odoo/addons/project_task_identification/README.rst
odoo/addons/project_task_identification/__init__.py
odoo/addons/project_task_identification/__manifest__.py
odoo/addons/project_task_identification/i18n/ca_ES.po
odoo/addons/project_task_identification/i18n/es.po
odoo/addons/project_task_identification/models/__init__.py
odoo/addons/project_task_identification/models/project_task.py
odoo/addons/project_task_identification/readme/CONTRIBUTORS.md
odoo/addons/project_task_identification/readme/DESCRIPTION.md
odoo/addons/project_task_identification/static/description/icon.png
odoo/addons/project_task_identification/static/description/index.html
odoo/addons/project_task_identification/tests/__init__.py
odoo/addons/project_task_identification/tests/test_project_task_identification.py
odoo/addons/project_task_identification/views/project_task_views.xml
odoo_addon_project_task_identification-18.0.1.1.0.1.dist-info/METADATA
odoo_addon_project_task_identification-18.0.1.1.0.1.dist-info/WHEEL
odoo_addon_project_task_identification-18.0.1.1.0.1.dist-info/top_level.txt
odoo_addon_project_task_identification-18.0.1.1.0.1.dist-info/RECORD
